{
  "classname": null,
  "name": null,
  "animation": {
    "classname": null,
    "name": "AnimationManager",
    "actionlist": []
  },
  "dataScale": 1,
  "designHeight": 640,
  "designWidth": 1200,
  "textures": [],
  "texturesPng": [
    "img/bg_jiugongge_4center.png",
    "button/btn_kfzy.png"
  ],
  "version": "1.6.0.0",
  "widgetTree": {
    "classname": "Panel",
    "name": null,
    "children": [
      {
        "classname": "ImageView",
        "name": null,
        "children": [],
        "options": {
          "__type": "ImageViewSurrogate:#EditorCommon.JsonModel.Component.GUI",
          "classname": "ImageView",
          "name": "list_bg",
          "ZOrder": 0,
          "actiontag": 24590590,
          "anchorPointX": 0,
          "anchorPointY": 0,
          "classType": "CocoStudio.EngineAdapterWrap.CSImageView",
          "colorB": 255,
          "colorG": 255,
          "colorR": 255,
          "customProperty": "",
          "flipX": false,
          "flipY": false,
          "height": 112,
          "ignoreSize": false,
          "layoutParameter": null,
          "opacity": 255,
          "positionPercentX": 0,
          "positionPercentY": 0,
          "positionType": 0,
          "rotation": 0,
          "scaleX": 1,
          "scaleY": 1,
          "sizePercentX": 1,
          "sizePercentY": 1,
          "sizeType": 0,
          "tag": 62,
          "touchAble": false,
          "useMergedTexture": false,
          "visible": true,
          "width": 484,
          "x": 0,
          "y": 0,
          "capInsetsHeight": 1,
          "capInsetsWidth": 1,
          "capInsetsX": 143,
          "capInsetsY": 45,
          "fileName": null,
          "fileNameData": {
            "path": "img/bg_jiugongge_4center.png",
            "plistFile": "",
            "resourceType": 0
          },
          "scale9Enable": true,
          "scale9Height": 112,
          "scale9Width": 484
        }
      },
      {
        "classname": "Label",
        "name": null,
        "children": [],
        "options": {
          "__type": "LabelSurrogate:#EditorCommon.JsonModel.Component.GUI",
          "classname": "Label",
          "name": "name",
          "ZOrder": 1,
          "actiontag": 2367263,
          "anchorPointX": 0,
          "anchorPointY": 0.5,
          "classType": "CocoStudio.EngineAdapterWrap.CSLabel",
          "colorB": 151,
          "colorG": 213,
          "colorR": 237,
          "customProperty": "",
          "flipX": false,
          "flipY": false,
          "height": 27,
          "ignoreSize": true,
          "layoutParameter": null,
          "opacity": 255,
          "positionPercentX": 0.227272734,
          "positionPercentY": 0.526785731,
          "positionType": 0,
          "rotation": 0,
          "scaleX": 1,
          "scaleY": 1,
          "sizePercentX": 0.109504133,
          "sizePercentY": 0.241071433,
          "sizeType": 0,
          "tag": 100,
          "touchAble": false,
          "useMergedTexture": false,
          "visible": true,
          "width": 53,
          "x": 110,
          "y": 59,
          "areaHeight": 0,
          "areaWidth": 0,
          "fontFile": null,
          "fontName": "微软雅黑",
          "fontSize": 20,
          "hAlignment": 0,
          "text": "name",
          "touchScaleEnable": false,
          "vAlignment": 0
        }
      },
      {
        "classname": "Label",
        "name": null,
        "children": [],
        "options": {
          "__type": "LabelSurrogate:#EditorCommon.JsonModel.Component.GUI",
          "classname": "Label",
          "name": "zl",
          "ZOrder": 1,
          "actiontag": 17241673,
          "anchorPointX": 0.5,
          "anchorPointY": 0.5,
          "classType": "CocoStudio.EngineAdapterWrap.CSLabel",
          "colorB": 255,
          "colorG": 255,
          "colorR": 255,
          "customProperty": "",
          "flipX": false,
          "flipY": false,
          "height": 24,
          "ignoreSize": true,
          "layoutParameter": null,
          "opacity": 255,
          "positionPercentX": 0.6487603,
          "positionPercentY": 0.526785731,
          "positionType": 0,
          "rotation": 0,
          "scaleX": 1,
          "scaleY": 1,
          "sizePercentX": 0.111570247,
          "sizePercentY": 0.214285716,
          "sizeType": 0,
          "tag": 148,
          "touchAble": false,
          "useMergedTexture": false,
          "visible": true,
          "width": 54,
          "x": 314,
          "y": 59,
          "areaHeight": 0,
          "areaWidth": 0,
          "fontFile": null,
          "fontName": "微软雅黑",
          "fontSize": 18,
          "hAlignment": 0,
          "text": "战力：",
          "touchScaleEnable": false,
          "vAlignment": 0
        }
      },
      {
        "classname": "Panel",
        "name": null,
        "children": [],
        "options": {
          "__type": "PanelSurrogate:#EditorCommon.JsonModel.Component.GUI",
          "classname": "Panel",
          "name": "frame_bg",
          "ZOrder": 1,
          "actiontag": 60945241,
          "anchorPointX": 0,
          "anchorPointY": 0,
          "classType": "CocoStudio.EngineAdapterWrap.CSPanel",
          "colorB": 255,
          "colorG": 255,
          "colorR": 255,
          "customProperty": "",
          "flipX": false,
          "flipY": false,
          "height": 93,
          "ignoreSize": false,
          "layoutParameter": null,
          "opacity": 255,
          "positionPercentX": 0.03305785,
          "positionPercentY": 0.05357143,
          "positionType": 0,
          "rotation": 0,
          "scaleX": 1,
          "scaleY": 1,
          "sizePercentX": 0.181818187,
          "sizePercentY": 0.830357134,
          "sizeType": 0,
          "tag": 152,
          "touchAble": true,
          "useMergedTexture": false,
          "visible": true,
          "width": 88,
          "x": 16,
          "y": 6,
          "adaptScreen": false,
          "backGroundImage": null,
          "backGroundImageData": null,
          "backGroundScale9Enable": false,
          "bgColorB": 255,
          "bgColorG": 200,
          "bgColorOpacity": 100,
          "bgColorR": 150,
          "bgEndColorB": 255,
          "bgEndColorG": 200,
          "bgEndColorR": 150,
          "bgStartColorB": 255,
          "bgStartColorG": 255,
          "bgStartColorR": 255,
          "capInsetsHeight": 1,
          "capInsetsWidth": 1,
          "capInsetsX": 0,
          "capInsetsY": 0,
          "clipAble": false,
          "colorType": 0,
          "layoutType": 0,
          "vectorX": 0,
          "vectorY": -0.5
        }
      },
      {
        "classname": "Label",
        "name": null,
        "children": [],
        "options": {
          "__type": "LabelSurrogate:#EditorCommon.JsonModel.Component.GUI",
          "classname": "Label",
          "name": "zl1",
          "ZOrder": 1,
          "actiontag": 21233739,
          "anchorPointX": 0,
          "anchorPointY": 0.5,
          "classType": "CocoStudio.EngineAdapterWrap.CSLabel",
          "colorB": 1,
          "colorG": 209,
          "colorR": 255,
          "customProperty": "",
          "flipX": false,
          "flipY": false,
          "height": 24,
          "ignoreSize": true,
          "layoutParameter": null,
          "opacity": 255,
          "positionPercentX": 0.7066116,
          "positionPercentY": 0.526785731,
          "positionType": 0,
          "rotation": 0,
          "scaleX": 1,
          "scaleY": 1,
          "sizePercentX": 0.0227272734,
          "sizePercentY": 0.214285716,
          "sizeType": 0,
          "tag": 176,
          "touchAble": false,
          "useMergedTexture": false,
          "visible": true,
          "width": 11,
          "x": 342,
          "y": 59,
          "areaHeight": 0,
          "areaWidth": 0,
          "fontFile": null,
          "fontName": "微软雅黑",
          "fontSize": 18,
          "hAlignment": 0,
          "text": "0",
          "touchScaleEnable": false,
          "vAlignment": 0
        }
      },
      {
        "classname": "Panel",
        "name": null,
        "children": [],
        "options": {
          "__type": "PanelSurrogate:#EditorCommon.JsonModel.Component.GUI",
          "classname": "Panel",
          "name": "panel_buff",
          "ZOrder": 0,
          "actiontag": 2794612,
          "anchorPointX": 0,
          "anchorPointY": 0,
          "classType": "CocoStudio.EngineAdapterWrap.CSPanel",
          "colorB": 255,
          "colorG": 255,
          "colorR": 255,
          "customProperty": "",
          "flipX": false,
          "flipY": false,
          "height": 62,
          "ignoreSize": false,
          "layoutParameter": null,
          "opacity": 255,
          "positionPercentX": 0.227272734,
          "positionPercentY": 0.05357143,
          "positionType": 0,
          "rotation": 0,
          "scaleX": 0.700000048,
          "scaleY": 0.700000048,
          "sizePercentX": 0.148760334,
          "sizePercentY": 0.5535714,
          "sizeType": 0,
          "tag": 177,
          "touchAble": true,
          "useMergedTexture": false,
          "visible": true,
          "width": 72,
          "x": 110,
          "y": 6,
          "adaptScreen": false,
          "backGroundImage": null,
          "backGroundImageData": {
            "path": "button/btn_kfzy.png",
            "plistFile": "",
            "resourceType": 0
          },
          "backGroundScale9Enable": false,
          "bgColorB": 255,
          "bgColorG": 200,
          "bgColorOpacity": 100,
          "bgColorR": 150,
          "bgEndColorB": 255,
          "bgEndColorG": 200,
          "bgEndColorR": 150,
          "bgStartColorB": 255,
          "bgStartColorG": 255,
          "bgStartColorR": 255,
          "capInsetsHeight": 1,
          "capInsetsWidth": 1,
          "capInsetsX": 0,
          "capInsetsY": 0,
          "clipAble": false,
          "colorType": 0,
          "layoutType": 0,
          "vectorX": 0,
          "vectorY": -0.5
        }
      }
    ],
    "options": {
      "__type": "PanelSurrogate:#EditorCommon.JsonModel.Component.GUI",
      "classname": "Panel",
      "name": "ckzd_list",
      "ZOrder": 0,
      "actiontag": -1,
      "anchorPointX": 0,
      "anchorPointY": 0,
      "classType": "CocoStudio.EngineAdapterWrap.CSPanel",
      "colorB": 255,
      "colorG": 255,
      "colorR": 255,
      "customProperty": "",
      "flipX": false,
      "flipY": false,
      "height": 112,
      "ignoreSize": false,
      "layoutParameter": null,
      "opacity": 255,
      "positionPercentX": 0,
      "positionPercentY": 0,
      "positionType": 0,
      "rotation": 0,
      "scaleX": 1,
      "scaleY": 1,
      "sizePercentX": 1,
      "sizePercentY": 1,
      "sizeType": 0,
      "tag": 3113,
      "touchAble": true,
      "useMergedTexture": false,
      "visible": true,
      "width": 484,
      "x": 0,
      "y": 0,
      "adaptScreen": false,
      "backGroundImage": null,
      "backGroundImageData": null,
      "backGroundScale9Enable": false,
      "bgColorB": 255,
      "bgColorG": 200,
      "bgColorOpacity": 0,
      "bgColorR": 150,
      "bgEndColorB": 255,
      "bgEndColorG": 200,
      "bgEndColorR": 150,
      "bgStartColorB": 255,
      "bgStartColorG": 255,
      "bgStartColorR": 255,
      "capInsetsHeight": 1,
      "capInsetsWidth": 1,
      "capInsetsX": 0,
      "capInsetsY": 0,
      "clipAble": false,
      "colorType": 1,
      "layoutType": 0,
      "vectorX": 0,
      "vectorY": -0.5
    }
  }
}