{"id":104,"level":{"rows":9.0,"columns":9.0,"starlevel":[2000.0,10000.0,20000.0],"version":0.0,"defaultRoomParameters":{"column":-1.0,"isBeginRoom":false,"isTreasureRoom":false,"row":-1.0,"roomRules":[{"type":"DiamondColorRule","fixedColors":[],"colors":3.0}]},"roomsParameters":[{"isBeginRoom":true,"isTreasureRoom":false,"row":0.0,"column":4.0,"boardMatrix":[["",0.0],["",3.0],["",3.0],["",3.0],["",3.0],["",3.0],[5.0,0.0],["",1.0],["",1.0],["",0.0],["",3.0],["",3.0],["",3.0],["",3.0],["",3.0],[6.0,0.0],["",1.0],["",1.0],["",0.0],["",1.0],["",1.0],["",1.0],["",1.0],["",1.0],["",1.0],["",1.0],["",1.0],["",0.0],["",1.0],["",1.0],["",1.0],["",1.0],["",1.0],["",1.0],["",1.0],["",1.0],["",0.0],["",3.0],["",3.0],["",3.0],["",3.0],["",3.0],["",1.0],["",1.0],["",1.0],["",0.0],["",3.0],["",3.0],["",3.0],["",3.0],["",3.0],["",1.0],["",1.0],["",1.0],["",0.0],["",0.0],["",0.0],["",0.0],["",0.0],["",0.0],["",1.0],["",1.0],["",1.0],["",0.0],["",3.0],["",3.0],["",3.0],["",3.0],["",0.0],["",1.0],["",1.0],["",1.0],["",0.0],["",3.0],["",3.0],["",3.0],["",3.0],["",0.0],["",0.0],["",0.0],["",0.0]],"roomRules":[{"type":"DiamondColorRule","fixedColors":[],"colors":3.0}]},{"isBeginRoom":false,"isTreasureRoom":false,"row":1.0,"usedColors":[0.0],"column":4.0,"boardMatrix":[["",1.0],["",1.0],["",1.0],["",0.0],["",0.0],["",0.0],["",0.0],["",0.0],["",0.0],["",3.0],["",3.0],["",3.0],["",0.0],["",3.0],["",3.0],[5.0,0.0],["",1.0],["",1.0],["",3.0],["",3.0],["",3.0],["",0.0],["",3.0],["",3.0],[6.0,0.0],["",1.0],["",1.0],["",1.0],["",1.0],["",1.0],[5.0,0.0],["",1.0],["",1.0],["",1.0],["",1.0],["",1.0],["",1.0],["",1.0],["",1.0],[6.0,0.0],["",1.0],["",1.0],["",1.0],["",1.0],["",1.0],["",3.0],["",3.0],["",1.0],["",1.0],["",3.0],["",3.0],["",1.0],["",1.0],["",1.0],["",3.0],["",3.0],["",1.0],["",1.0],["",3.0],["",3.0],["",1.0],["",1.0],["",1.0],["",1.0],["",1.0],["",1.0],["",1.0],["",1.0],["",1.0],["",1.0],["",1.0],["",1.0],["",1.0],["",1.0],["",1.0],[0.0,1.0],[0.0,1.0],["",1.0],["",3.0],["",3.0],["",3.0]],"roomRules":[{"type":"DiamondColorRule","fixedColors":[],"colors":3.0}]},{"isBeginRoom":false,"isTreasureRoom":false,"row":2.0,"column":4.0,"boardMatrix":[["",0.0],["",1.0,2.0],["",1.0],["",0.0],["",0.0],["",0.0],[5.0,0.0],["",1.0],["",1.0],["",0.0],["",1.0,2.0],["",1.0],["",0.0],["",1.0],["",1.0],[6.0,0.0],["",1.0],["",1.0],["",0.0],["",1.0,2.0],["",1.0],["",0.0],["",1.0],["",1.0],["",1.0],["",1.0],["",1.0],["",0.0],["",1.0,2.0],["",1.0],[5.0,0.0],["",1.0],["",1.0],["",3.0],["",3.0],["",3.0],["",0.0],["",1.0],["",1.0],[6.0,0.0],["",1.0],["",1.0],["",3.0],["",3.0],["",3.0],[5.0,0.0],["",1.0],["",1.0],["",1.0],["",1.0],["",1.0],["",1.0],["",1.0],["",1.0],[6.0,0.0],["",1.0],["",1.0],["",3.0],["",3.0],["",1.0],["",1.0],["",1.0],["",1.0,2.0],["",1.0],["",1.0],["",1.0],["",3.0],["",3.0],["",1.0],["",1.0],["",1.0],["",1.0,2.0],["",1.0],["",0.0],["",1.0],["",1.0],["",1.0],["",1.0],["",1.0],["",1.0],["",1.0,2.0]],"roomRules":[{"type":"DiamondColorRule","fixedColors":[],"colors":3.0}]},{"isBeginRoom":false,"isTreasureRoom":false,"row":3.0,"usedColors":[1.0],"column":4.0,"boardMatrix":[["",0.0],["",1.0],["",3.0],["",0.0],["",3.0],["",1.0],["",0.0],["",1.0],["",1.0,3.0],[5.0,0.0],["",1.0],["",3.0],[5.0,0.0],["",3.0],["",1.0],[5.0,0.0],["",1.0],["",1.0,3.0],[6.0,0.0],["",1.0],["",1.0],[6.0,0.0],["",1.0],["",1.0],[6.0,0.0],["",1.0],["",1.0,3.0],["",1.0],["",1.0],["",1.0],["",1.0],["",1.0],["",1.0],["",1.0],["",3.0],["",3.0],["",1.0],["",1.0],["",1.0],["",1.0],["",1.0,3.0],["",1.0],["",1.0],["",3.0],["",3.0],["",1.0],["",1.0],["",1.0],["",1.0],["",1.0],["",1.0],["",1.0],["",1.0,3.0],["",1.0,3.0],["",1.0],["",1.0],["",1.0],["",1.0],["",1.0],["",1.0],["",1.0],["",1.0,3.0],["",1.0,3.0],["",1.0],["",1.0],["",1.0],["",1.0],["",1.0],["",1.0],["",1.0],["",1.0],["",1.0],[1.0,1.0],["",3.0],["",3.0],[1.0,1.0],["",3.0],["",3.0],[1.0,1.0],["",3.0],["",3.0]],"roomRules":[{"fixed":true,"type":"DiamondColorRule","colors":3.0,"fixedColors":[{"percentage":34.0,"color":3.0},{"percentage":33.0,"color":0.0},{"percentage":33.0,"color":2.0}]}]}],"id":0.0,"starLevelDef":{"oneStarScore":2000.0,"twoStarScore":10000.0,"threeStarScore":20000.0},"randomVariableSeed":8.78244633E8,"doorsParameters":[{"numberOfAccessibleObjectsToLeft":0.0,"row":15.0,"column":40.0,"positionInRoom":2.0,"numberOfAccessibleObjectsToDown":0.0,"numberOfAccessibleObjectsToRight":0.0},{"numberOfAccessibleObjectsToLeft":0.0,"row":-5.0,"isEntrance":true,"column":40.0,"positionInRoom":0.0,"numberOfAccessibleObjectsToDown":0.0,"numberOfAccessibleObjectsToRight":0.0},{"numberOfAccessibleObjectsToLeft":0.0,"row":5.0,"column":40.0,"positionInRoom":8.0,"numberOfAccessibleObjectsToDown":0.0,"numberOfAccessibleObjectsToRight":0.0},{"numberOfAccessibleObjectsToLeft":0.0,"row":25.0,"column":40.0,"positionInRoom":1.0,"numberOfAccessibleObjectsToDown":0.0,"numberOfAccessibleObjectsToRight":0.0}],"existences":{"hasTimeBomb":false,"hasDoorActivator":false,"hasPassingBigRock":false,"hasFrozenJewel":false,"hasColoredExit":false,"hasMultiClearRock":false,"hasIndestructibleBigRock":false,"hasDestructibleBigRock":false,"hasToken":false,"hasToysGenerator":false,"hasGroundGeneratorMulticlear_1":false,"hasCoinGround":false,"hasExplode":false,"hasFreezer":false},"initialMoves":26.0,"isLevelHard":false,"orbType":"colorBomb","gameMode":{"type":"totem","objectRequirements":9.0},"diamondsToFillOrb":100.0},"version":9}