{"id":305,"level":{"initialMoves":22.0,"isLevelHard":false,"orbType":"fourWayLB","existences":{"hasIndestructibleBigRock":false,"hasFreezerLine":false,"hasDestructibleBigRock":false,"hasToken":false,"hasToysGenerator":false,"hasCoinGround":true,"hasFreezer":false,"hasLavaBomb":false,"hasExplode":false,"hasTimeBomb":false,"hasChameleon":false,"hasDoorActivator":false,"hasGroundGeneratorMulticlear_1":false,"hasPassingBigRock":false,"hasFrozenJewel":false,"hasLava":false,"hasMultiClearRock":false,"hasColoredExit":true},"diamondsToFillOrb":100.0,"version":0.0,"doorsParameters":[{"numberOfAccessibleObjectsToRight":0.0,"column":40.0,"numberOfAccessibleObjectsToLeft":0.0,"colorLocked":{"min":25.0,"max":25.0,"diamondIndex":1.0},"positionInRoom":8.0,"numberOfAccessibleObjectsToDown":0.0,"row":5.0},{"numberOfAccessibleObjectsToRight":0.0,"column":40.0,"numberOfAccessibleObjectsToLeft":0.0,"colorLocked":{"min":50.0,"max":50.0,"diamondIndex":1.0},"positionInRoom":4.0,"numberOfAccessibleObjectsToDown":0.0,"row":25.0},{"numberOfAccessibleObjectsToRight":0.0,"column":40.0,"numberOfAccessibleObjectsToLeft":0.0,"positionInRoom":8.0,"isEntrance":true,"numberOfAccessibleObjectsToDown":0.0,"row":-5.0},{"numberOfAccessibleObjectsToRight":0.0,"column":40.0,"numberOfAccessibleObjectsToLeft":0.0,"colorLocked":{"min":30.0,"max":30.0,"diamondIndex":1.0},"positionInRoom":8.0,"numberOfAccessibleObjectsToDown":0.0,"row":15.0}],"id":0.0,"randomVariableSeed":8.78244633E8,"columns":9.0,"roomsParameters":[{"usedColors":[1.0,2.0],"column":4.0,"isBeginRoom":true,"roomRules":[{"fixedColors":[],"type":"DiamondColorRule","colors":3.0}],"isTreasureRoom":false,"boardMatrix":[["",1.0],["",1.0],["",1.0],["",3.0],["",1.0,"",4.0],["",3.0],["",1.0,"",7.0],["",3.0],["",1.0],["",1.0],["",1.0],["",1.0],["",3.0],["",1.0,"",4.0],["",3.0],["",1.0,"",7.0],["",3.0],["",1.0],["",16.0],["",16.0],["",16.0],["",3.0],[1.0,1.0,"",4.0],["",3.0],[2.0,1.0,"",7.0],["",3.0],["",1.0],["",16.0],["",16.0],["",16.0],["",3.0],[1.0,1.0,"",4.0],["",3.0],[2.0,1.0,"",7.0],["",3.0],["",1.0],["",16.0],["",16.0],["",16.0],["",3.0],[1.0,1.0,"",4.0],["",3.0],[2.0,1.0,"",7.0],["",3.0],["",1.0],["",15.0],["",15.0],["",15.0],["",3.0],["",1.0,"",4.0],["",3.0],["",1.0,"",7.0],["",3.0],["",1.0],["",15.0],["",15.0],["",15.0],["",3.0],["",1.0,"",4.0],["",3.0],["",1.0,"",7.0],["",3.0],["",1.0],["",15.0],["",15.0],["",15.0],["",3.0],["",1.0,"",4.0],["",3.0],["",1.0,"",7.0],["",3.0],["",1.0],["",15.0],["",15.0],["",15.0],["",3.0],["",1.0,"",4.0],["",3.0],["",1.0,"",7.0],["",3.0],["",1.0]],"columnRules":[{"rules":[{"percentage":50.0,"type":"PowerUpRule","powerUpRuleParams":[{"percentage":100.0,"type":4.0}]}],"columnNumber":4.0},{"rules":[{"percentage":50.0,"type":"PowerUpRule","powerUpRuleParams":[{"percentage":100.0,"type":7.0}]}],"columnNumber":6.0}],"row":0.0},{"usedColors":[1.0],"column":4.0,"isBeginRoom":false,"roomRules":[{"fixedColors":[],"type":"DiamondColorRule","colors":3.0}],"isTreasureRoom":false,"boardMatrix":[["",1.0],["",1.0],["",1.0],["",1.0],["",1.0],["",1.0],["",1.0],["",1.0],["",1.0],["",1.0],["",3.0],["",3.0],["",3.0],["",3.0],["",3.0],["",3.0],["",3.0],["",3.0],["",1.0],["",3.0],["",1.0,"",7.0],["",1.0,"",3.0],["",3.0],["",16.0],["",16.0],["",16.0],["",16.0],["",1.0],["",3.0],["",1.0,"",7.0],["",1.0,"",3.0],["",3.0],["",15.0],["",15.0],["",15.0],["",15.0],["",1.0],["",3.0],["",1.0,"",7.0],["",1.0,"",3.0],["",3.0],["",15.0],["",15.0],["",15.0],["",15.0],["",1.0],["",3.0],["",1.0,"",7.0],["",1.0,"",3.0],["",3.0],["",15.0],["",15.0],["",15.0],["",15.0],["",1.0],["",3.0],["",1.0,"",7.0],["",1.0,"",3.0],["",3.0],["",15.0],["",15.0],["",15.0],["",15.0],["",1.0],["",3.0],["",3.0],["",3.0],["",3.0],["",3.0],["",3.0],["",3.0],["",3.0],[1.0,1.0],["",1.0],["",1.0],["",1.0],["",1.0],["",1.0],["",1.0],["",1.0],["",1.0]],"columnRules":[{"rules":[{"percentage":50.0,"type":"PowerUpRule","powerUpRuleParams":[{"percentage":100.0,"type":7.0}]}],"columnNumber":2.0},{"rules":[{"percentage":50.0,"type":"PowerUpRule","powerUpRuleParams":[{"percentage":100.0,"type":4.0}]}],"columnNumber":3.0}],"row":1.0},{"usedColors":[1.0],"column":4.0,"isBeginRoom":false,"roomRules":[{"fixedColors":[],"type":"DiamondColorRule","colors":3.0}],"isTreasureRoom":false,"boardMatrix":[["",1.0],["",1.0],["",1.0],["",1.0],["",1.0],["",1.0],["",1.0],["",1.0],["",1.0],["",1.0],["",1.0],["",1.0],["",1.0],["",1.0],["",1.0],["",1.0],["",1.0],["",1.0],["",1.0,"",7.0],["",1.0],["",3.0],["",3.0],["",19.0],["",3.0],["",3.0],["",1.0],["",1.0,"",7.0],["",1.0,"",7.0],["",1.0],["",3.0],["",15.0],["",15.0],["",15.0],["",3.0],["",1.0],["",1.0,"",7.0],["",1.0,"",7.0],["",1.0],["",3.0],["",16.0],["",16.0],["",16.0],["",3.0],["",1.0],["",1.0,"",7.0],["",1.0,"",7.0],["",1.0],["",3.0],["",16.0],["",16.0],["",16.0],["",3.0],["",1.0],["",1.0,"",7.0],["",1.0,"",7.0],["",1.0],["",3.0],["",16.0],["",16.0],["",16.0],["",3.0],["",1.0],["",1.0,"",7.0],["",1.0,"",7.0],["",1.0],["",3.0],["",16.0],["",16.0],["",16.0],["",3.0],["",1.0],["",1.0,"",7.0],["",1.0,"",7.0],[1.0,1.0],["",3.0],["",16.0],["",17.0],["",16.0],["",3.0],["",1.0],["",1.0,"",7.0]],"columnRules":[{"rules":[{"percentage":50.0,"type":"PowerUpRule","powerUpRuleParams":[{"percentage":100.0,"type":7.0}]}],"columnNumber":0.0},{"rules":[{"percentage":50.0,"type":"PowerUpRule","powerUpRuleParams":[{"percentage":100.0,"type":7.0}]}],"columnNumber":8.0}],"row":2.0},{"usedColors":[1.0],"column":4.0,"isBeginRoom":false,"roomRules":[{"fixedColors":[],"type":"DiamondColorRule","colors":3.0}],"isTreasureRoom":true,"boardMatrix":[["",0.0],["",0.0],["",0.0],["",0.0],["",0.0],["",0.0],["",0.0],["",0.0],["",0.0],["",0.0],["",0.0],["",0.0],["",0.0],["",0.0],["",0.0],["",0.0],["",0.0],["",0.0],["",0.0],["",0.0],["",0.0],["",0.0],["",0.0],["",0.0],["",0.0],["",0.0],["",0.0],["",0.0],["",0.0],["",0.0],["",0.0],["",0.0],["",0.0],["",0.0],["",0.0],["",0.0],["",0.0],["",0.0],["",0.0],["",0.0],["",0.0],["",0.0],["",0.0],["",0.0],["",0.0],["",0.0],["",0.0],["",0.0],["",0.0],["",0.0],["",0.0],["",0.0],["",0.0],["",0.0],["",0.0],["",0.0],["",0.0],["",0.0],["",0.0],["",0.0],["",0.0],["",0.0],["",0.0],["",0.0],[1.0,0.0],[1.0,0.0],["",0.0],["",0.0],["",0.0],["",0.0],["",0.0],["",0.0],["",0.0],[1.0,0.0],[1.0,0.0],["",0.0],["",0.0],["",0.0],["",0.0],["",0.0],["",0.0]],"row":3.0}],"starLevelDef":{"threeStarScore":200000.0,"oneStarScore":185000.0,"twoStarScore":195000.0},"starlevel":[185000.0,195000.0,200000.0],"defaultRoomParameters":{"roomRules":[{"fixedColors":[],"type":"DiamondColorRule","colors":3.0}],"isTreasureRoom":false,"column":-1.0,"isBeginRoom":false,"row":-1.0},"rows":9.0,"gameMode":{"objectRequirements":0.0,"type":"reachTargetScore"}},"version":4}